commandict/__init__.py
commandict/get_result.py
commandict-0.1.4.dist-info/LICENSE
commandict-0.1.4.dist-info/METADATA
commandict-0.1.4.dist-info/WHEEL
commandict-0.1.4.dist-info/entry_points.txt
commandict-0.1.4.dist-info/top_level.txt
commandict-0.1.4.dist-info/RECORD
